flspp/__init__.py
flspp/_core.cp39-win_amd64.pyd
flspp/_core.cpp
flspp/core.py
flspp/cpp/additional_vector_stuff.h
flspp/cpp/clustering.cpp
flspp/cpp/clustering.h
flspp/cpp/clustering_algorithm.cpp
flspp/cpp/clustering_algorithm.h
flspp/cpp/makros.cpp
flspp/cpp/makros.h
flspp/cpp/random_generator.cpp
flspp/cpp/random_generator.h
flspp_modified-1.4.dist-info/METADATA
flspp_modified-1.4.dist-info/WHEEL
flspp_modified-1.4.dist-info/top_level.txt
flspp_modified-1.4.dist-info/RECORD
