Metadata-Version: 2.1
Name: flspp-modified
Version: 1.4
Summary: Implementation of the FLS++ algorithm for K-Means clustering.
Home-page: UNKNOWN
License: UNKNOWN
Platform: UNKNOWN
Requires-Python: >=3.9,<4.0
Requires-Dist: numpy (>=1.22.4)
Requires-Dist: scikit-learn (==0.23.2)
